erp5_coverage_plugin/__init__.py
erp5_coverage_plugin-0.0.2.dist-info/METADATA
erp5_coverage_plugin-0.0.2.dist-info/WHEEL
erp5_coverage_plugin-0.0.2.dist-info/top_level.txt
erp5_coverage_plugin-0.0.2.dist-info/RECORD
