Metadata-Version: 2.1
Name: erp5_coverage_plugin
Version: 0.0.2
Summary: Coverage plugin for ERP5 python scripts and components
Project-URL: Homepage, https://lab.nexedi.com/nexedi/erp5_coverage_plugin
Requires-Python: >=3.9
Requires-Dist: coverage <8,>=7.6
Provides-Extra: test
Requires-Dist: pytest ; extra == 'test'
Requires-Dist: Products.PythonScripts ; extra == 'test'
